enil/__init__.py
enil/akad/AccountSupervisorService.py
enil/akad/AgeCheckService.py
enil/akad/AuthService.py
enil/akad/BotService.py
enil/akad/BuddyManagementService.py
enil/akad/BuddyService.py
enil/akad/CallService.py
enil/akad/ChannelApplicationProvidedService.py
enil/akad/ChannelService.py
enil/akad/LiffService.py
enil/akad/LongpollingService.py
enil/akad/MessageService.py
enil/akad/ShopService.py
enil/akad/SnsAdaptorService.py
enil/akad/SpotService.py
enil/akad/SquareService.py
enil/akad/TalkService.py
enil/akad/TicketService.py
enil/akad/UniversalNotificationService.py
enil/akad/__init__.py
enil/akad/constants.py
enil/akad/ttypes.py
enil/linepy/__init__.py
enil/linepy/auth.py
enil/linepy/call.py
enil/linepy/callback.py
enil/linepy/channel.py
enil/linepy/client.py
enil/linepy/config.py
enil/linepy/e2ee.py
enil/linepy/liff.py
enil/linepy/login.py
enil/linepy/models.py
enil/linepy/object.py
enil/linepy/oepoll.py
enil/linepy/server.py
enil/linepy/session.py
enil/linepy/shop.py
enil/linepy/square.py
enil/linepy/talk.py
enil/linepy/timeline.py
enil/linepy/transport.py
enil-0.2.2.dist-info/LICENSE
enil-0.2.2.dist-info/WHEEL
enil-0.2.2.dist-info/METADATA
enil-0.2.2.dist-info/RECORD
