Metadata-Version: 2.1
Name: enil
Version: 0.2.2
Summary: 
Author:  
Requires-Python: >=3.7,<4
Classifier: Programming Language :: Python :: 3
Classifier: Programming Language :: Python :: 3.10
Classifier: Programming Language :: Python :: 3.7
Classifier: Programming Language :: Python :: 3.8
Classifier: Programming Language :: Python :: 3.9
Requires-Dist: PyQRCode (>=1.2.1,<2.0.0)
Requires-Dist: httplib2 (>=0.20.4,<0.21.0)
Requires-Dist: httpx (>=0.23.0,<0.24.0)
Requires-Dist: hyper (>=0.7.0,<0.8.0)
Requires-Dist: lesting.api.client (>=0.1.1,<0.2.0)
Requires-Dist: pycryptodome (>=3.15.0,<4.0.0)
Requires-Dist: python-axolotl-curve25519 (>=0.4.1,<0.5.0)
Requires-Dist: requests (>=2.28.0,<3.0.0)
Requires-Dist: rsa (>=4.8,<5.0)
Requires-Dist: thrift (>=0.16.0,<0.17.0)
Requires-Dist: toml (>=0.10.2,<0.11.0)
